ibek/__init__.py
ibek/__main__.py
ibek/_version.py
ibek/commands.py
ibek/entity_factory.py
ibek/entity_model.py
ibek/gen_scripts.py
ibek/globals.py
ibek/ioc.py
ibek/ioc_factory.py
ibek/parameters.py
ibek/render.py
ibek/render_db.py
ibek/sub_entity.py
ibek/support.py
ibek/utils.py
ibek/dev_cmds/__init__.py
ibek/dev_cmds/commands.py
ibek/ibek_builtin/__init__.py
ibek/ibek_builtin/built_ins.py
ibek/ibek_builtin/repeat.py
ibek/ioc_cmds/__init__.py
ibek/ioc_cmds/assets.py
ibek/ioc_cmds/commands.py
ibek/ioc_cmds/docker.py
ibek/runtime_cmds/__init__.py
ibek/runtime_cmds/autosave.py
ibek/runtime_cmds/commands.py
ibek/support_cmds/__init__.py
ibek/support_cmds/checks.py
ibek/support_cmds/commands.py
ibek/support_cmds/files.py
ibek/templates/ioc.subst.jinja
ibek/templates/st.cmd.jinja
ibek/templates/support/Makefile
ibek/templates/support/configure/RELEASE
ibek-3.2.3.dist-info/licenses/LICENSE
ibek-3.2.3.dist-info/METADATA
ibek-3.2.3.dist-info/WHEEL
ibek-3.2.3.dist-info/entry_points.txt
ibek-3.2.3.dist-info/top_level.txt
ibek-3.2.3.dist-info/RECORD
