Metadata-Version: 2.4
Name: ibek
Version: 3.2.3
Summary: IOC builder for EPICS and Kubernetes
Author-email: Giles Knap <giles.knap@diamond.ac.uk>
License:                                  Apache License
Project-URL: GitHub, https://github.com/epics-containers/ibek
Classifier: Development Status :: 3 - Alpha
Classifier: License :: OSI Approved :: Apache Software License
Classifier: Programming Language :: Python :: 3.10
Classifier: Programming Language :: Python :: 3.11
Classifier: Programming Language :: Python :: 3.12
Requires-Python: >=3.10
License-File: LICENSE
Requires-Dist: pydantic==2.8.2
Requires-Dist: typer
Requires-Dist: click<8.2
Requires-Dist: ruamel.yaml
Requires-Dist: jinja2
Requires-Dist: GitPython
Requires-Dist: semantic-version
Requires-Dist: pvi
Provides-Extra: dev
Requires-Dist: copier; extra == "dev"
Requires-Dist: mypy; extra == "dev"
Requires-Dist: myst-parser; extra == "dev"
Requires-Dist: pipdeptree; extra == "dev"
Requires-Dist: pre-commit; extra == "dev"
Requires-Dist: pydata-sphinx-theme>=0.12; extra == "dev"
Requires-Dist: pytest; extra == "dev"
Requires-Dist: pytest-cov; extra == "dev"
Requires-Dist: pytest-mock; extra == "dev"
Requires-Dist: ruff; extra == "dev"
Requires-Dist: sphinx-autobuild; extra == "dev"
Requires-Dist: sphinx-copybutton; extra == "dev"
Requires-Dist: sphinx-design; extra == "dev"
Requires-Dist: tox-direct; extra == "dev"
Requires-Dist: types-mock; extra == "dev"
Requires-Dist: types-requests; extra == "dev"
Dynamic: license-file
